redast/__init__.py
redast/__init__.pyi
redast/__version__.py
redast/__version__.pyi
redast/py.typed
redast/core/__init__.py
redast/core/__init__.pyi
redast/core/hash.py
redast/core/hash.pyi
redast/core/packaging.py
redast/core/packaging.pyi
redast/core/storage.py
redast/core/storage.pyi
redast/local/__init__.py
redast/local/__init__.pyi
redast/local/cache.py
redast/local/cache.pyi
redast/local/drive.py
redast/local/drive.pyi
redast/local/memory.py
redast/local/memory.pyi
redast/local/sqlite.py
redast/local/sqlite.pyi
redast/remote/__init__.py
redast/remote/__init__.pyi
redast/tool/__init__.py
redast/tool/__init__.pyi
redast/tool/io.py
redast/tool/io.pyi
redast-0.1.8.dist-info/LICENSE
redast-0.1.8.dist-info/METADATA
redast-0.1.8.dist-info/WHEEL
redast-0.1.8.dist-info/top_level.txt
redast-0.1.8.dist-info/RECORD
